{
  "bootstrapComplete": true,
  "bootstrapPicksProcessed": 1545,
  "bootstrapRunAt": "2026-03-24T22:12:41.194Z",
  "totalLearningCycles": 88,
  "lastCycleAt": "2026-03-25T00:01:55.776Z",
  "lastCycleSettledCount": 1,
  "userFeedbackProcessed": 0,
  "mcEngineRecords": 1513,
  "mcStackedCycles": 88,
  "usmlCycles": 88,
  "sportAccuracy": {
    "NBA": {
      "wins": 277,
      "total": 489,
      "winRate": 0.5664621676891616
    },
    "NHL": {
      "wins": 248,
      "total": 468,
      "winRate": 0.5299145299145299
    },
    "NCAAB": {
      "wins": 266,
      "total": 439,
      "winRate": 0.6059225512528473
    },
    "MLB": {
      "wins": 75,
      "total": 117,
      "winRate": 0.6410256410256411
    }
  },
  "errors": []
}