{
  "totalPatterns": 33,
  "toxicPatterns": 13,
  "goldenPatterns": 19,
  "totalSettledPicks": 1102,
  "lastRunAt": "2026-03-12T20:06:31.299Z",
  "nextRunAt": "2026-03-12T20:26:31.299Z",
  "patterns": [
    {
      "id": "learned-NBA-moneyline-heavy_underdog",
      "type": "golden",
      "sport": "NBA",
      "betType": "moneyline",
      "oddsRange": "heavy_underdog",
      "sampleSize": 14,
      "wins": 12,
      "losses": 2,
      "winRate": 0.8571428571428571,
      "expectedWinRate": 0.21892103205629398,
      "edge": 0.6382218250865631,
      "adjustmentAmount": 7,
      "description": "NBA ML (heavy underdog) outperforms market expectations by 64%",
      "positiveCue": "NBA ML (heavy underdog) tracking at 86% (expected 22%) across 14 picks — model generating edge here",
      "lastUpdated": "2026-03-12T20:06:31.298Z",
      "dataSource": "combined",
      "statisticalConfidence": 0.55
    },
    {
      "id": "learned-NBA-moneyline",
      "type": "golden",
      "sport": "NBA",
      "betType": "moneyline",
      "sampleSize": 251,
      "wins": 139,
      "losses": 112,
      "winRate": 0.5537848605577689,
      "expectedWinRate": 0.3966636219412528,
      "edge": 0.15712123861651606,
      "adjustmentAmount": 7,
      "description": "NBA ML outperforms market expectations by 16%",
      "positiveCue": "NBA ML tracking at 55% (expected 40%) across 251 picks — model generating edge here",
      "lastUpdated": "2026-03-12T20:06:31.298Z",
      "dataSource": "combined",
      "statisticalConfidence": 0.95
    },
    {
      "id": "learned-all-moneyline-heavy_underdog",
      "type": "golden",
      "sport": "all",
      "betType": "moneyline",
      "oddsRange": "heavy_underdog",
      "sampleSize": 15,
      "wins": 12,
      "losses": 3,
      "winRate": 0.8,
      "expectedWinRate": 0.22281639928698752,
      "edge": 0.5771836007130126,
      "adjustmentAmount": 7,
      "description": "All sports ML (heavy underdog) outperforms market expectations by 58%",
      "positiveCue": "All sports ML (heavy underdog) tracking at 80% (expected 22%) across 15 picks — model generating edge here",
      "lastUpdated": "2026-03-12T20:06:31.298Z",
      "dataSource": "combined",
      "statisticalConfidence": 0.55
    },
    {
      "id": "learned-NBA-moneyline-B_tier",
      "type": "golden",
      "sport": "NBA",
      "betType": "moneyline",
      "oddsRange": "B_tier",
      "sampleSize": 27,
      "wins": 14,
      "losses": 13,
      "winRate": 0.5185185185185185,
      "expectedWinRate": 0.0762914813547725,
      "edge": 0.442227037163746,
      "adjustmentAmount": 7,
      "description": "NBA ML (B tier) outperforms market expectations by 44%",
      "positiveCue": "NBA ML (B tier) tracking at 52% (expected 8%) across 27 picks — model generating edge here",
      "lastUpdated": "2026-03-12T20:06:31.298Z",
      "dataSource": "combined",
      "statisticalConfidence": 0.72
    },
    {
      "id": "learned-all-moneyline-heavy_favorite",
      "type": "toxic",
      "sport": "all",
      "betType": "moneyline",
      "oddsRange": "heavy_favorite",
      "sampleSize": 37,
      "wins": 20,
      "losses": 17,
      "winRate": 0.5405405405405406,
      "expectedWinRate": 0.8743590614282318,
      "edge": -0.33381852088769126,
      "adjustmentAmount": -14,
      "description": "All sports ML (heavy favorite) underperforms market expectations by 33%",
      "warningText": "All sports ML (heavy favorite) tracking at 54% (expected 87%) across 37 picks — pattern shows below-market performance",
      "lastUpdated": "2026-03-12T20:06:31.298Z",
      "dataSource": "combined",
      "statisticalConfidence": 0.72
    },
    {
      "id": "learned-NBA-moneyline-C_tier",
      "type": "toxic",
      "sport": "NBA",
      "betType": "moneyline",
      "oddsRange": "C_tier",
      "sampleSize": 56,
      "wins": 30,
      "losses": 26,
      "winRate": 0.5357142857142857,
      "expectedWinRate": 0.7178566850403794,
      "edge": -0.18214239932609366,
      "adjustmentAmount": -14,
      "description": "NBA ML (C tier) underperforms market expectations by 18%",
      "warningText": "NBA ML (C tier) tracking at 54% (expected 72%) across 56 picks — pattern shows below-market performance",
      "lastUpdated": "2026-03-12T20:06:31.298Z",
      "dataSource": "combined",
      "statisticalConfidence": 0.85
    },
    {
      "id": "learned-NHL-moneyline",
      "type": "golden",
      "sport": "NHL",
      "betType": "moneyline",
      "sampleSize": 216,
      "wins": 129,
      "losses": 87,
      "winRate": 0.5972222222222222,
      "expectedWinRate": 0.4848065639460001,
      "edge": 0.11241565827622213,
      "adjustmentAmount": 6,
      "description": "NHL ML outperforms market expectations by 11%",
      "positiveCue": "NHL ML tracking at 60% (expected 48%) across 216 picks — model generating edge here",
      "lastUpdated": "2026-03-12T20:06:31.298Z",
      "dataSource": "combined",
      "statisticalConfidence": 0.95
    },
    {
      "id": "learned-NHL-moneyline-B_tier",
      "type": "golden",
      "sport": "NHL",
      "betType": "moneyline",
      "oddsRange": "B_tier",
      "sampleSize": 24,
      "wins": 17,
      "losses": 7,
      "winRate": 0.7083333333333334,
      "expectedWinRate": 0.5066803699897225,
      "edge": 0.20165296334361082,
      "adjustmentAmount": 7,
      "description": "NHL ML (B tier) outperforms market expectations by 20%",
      "positiveCue": "NHL ML (B tier) tracking at 71% (expected 51%) across 24 picks — model generating edge here",
      "lastUpdated": "2026-03-12T20:06:31.298Z",
      "dataSource": "combined",
      "statisticalConfidence": 0.72
    },
    {
      "id": "learned-NHL-spread-underdog",
      "type": "toxic",
      "sport": "NHL",
      "betType": "spread",
      "oddsRange": "underdog",
      "sampleSize": 10,
      "wins": 2,
      "losses": 8,
      "winRate": 0.2,
      "expectedWinRate": 0.37551633496057074,
      "edge": -0.17551633496057073,
      "adjustmentAmount": -14,
      "description": "NHL spreads (underdog) underperforms market expectations by 18%",
      "warningText": "NHL spreads (underdog) tracking at 20% (expected 38%) across 10 picks — pattern shows below-market performance",
      "lastUpdated": "2026-03-12T20:06:31.298Z",
      "dataSource": "combined",
      "statisticalConfidence": 0.55
    },
    {
      "id": "learned-NHL-spread",
      "type": "golden",
      "sport": "NHL",
      "betType": "spread",
      "sampleSize": 86,
      "wins": 48,
      "losses": 38,
      "winRate": 0.5581395348837209,
      "expectedWinRate": 0.4440853264382676,
      "edge": 0.11405420844545333,
      "adjustmentAmount": 6,
      "description": "NHL spreads outperforms market expectations by 11%",
      "positiveCue": "NHL spreads tracking at 56% (expected 44%) across 86 picks — model generating edge here",
      "lastUpdated": "2026-03-12T20:06:31.298Z",
      "dataSource": "combined",
      "statisticalConfidence": 0.95
    },
    {
      "id": "learned-all-spread-underdog",
      "type": "toxic",
      "sport": "all",
      "betType": "spread",
      "oddsRange": "underdog",
      "sampleSize": 10,
      "wins": 2,
      "losses": 8,
      "winRate": 0.2,
      "expectedWinRate": 0.37551633496057074,
      "edge": -0.17551633496057073,
      "adjustmentAmount": -14,
      "description": "All sports spreads (underdog) underperforms market expectations by 18%",
      "warningText": "All sports spreads (underdog) tracking at 20% (expected 38%) across 10 picks — pattern shows below-market performance",
      "lastUpdated": "2026-03-12T20:06:31.298Z",
      "dataSource": "combined",
      "statisticalConfidence": 0.55
    },
    {
      "id": "learned-NHL-spread-B_tier",
      "type": "golden",
      "sport": "NHL",
      "betType": "spread",
      "oddsRange": "B_tier",
      "sampleSize": 22,
      "wins": 15,
      "losses": 7,
      "winRate": 0.6818181818181818,
      "expectedWinRate": 0.31613304320795776,
      "edge": 0.365685138610224,
      "adjustmentAmount": 7,
      "description": "NHL spreads (B tier) outperforms market expectations by 37%",
      "positiveCue": "NHL spreads (B tier) tracking at 68% (expected 32%) across 22 picks — model generating edge here",
      "lastUpdated": "2026-03-12T20:06:31.298Z",
      "dataSource": "combined",
      "statisticalConfidence": 0.72
    },
    {
      "id": "learned-NHL-spread-heavy_favorite",
      "type": "toxic",
      "sport": "NHL",
      "betType": "spread",
      "oddsRange": "heavy_favorite",
      "sampleSize": 8,
      "wins": 4,
      "losses": 4,
      "winRate": 0.5,
      "expectedWinRate": 0.7062063900110173,
      "edge": -0.20620639001101726,
      "adjustmentAmount": -14,
      "description": "NHL spreads (heavy favorite) underperforms market expectations by 21%",
      "warningText": "NHL spreads (heavy favorite) tracking at 50% (expected 71%) across 8 picks — pattern shows below-market performance",
      "lastUpdated": "2026-03-12T20:06:31.298Z",
      "dataSource": "combined",
      "statisticalConfidence": 0.3
    },
    {
      "id": "learned-all-spread-heavy_favorite",
      "type": "toxic",
      "sport": "all",
      "betType": "spread",
      "oddsRange": "heavy_favorite",
      "sampleSize": 8,
      "wins": 4,
      "losses": 4,
      "winRate": 0.5,
      "expectedWinRate": 0.7062063900110173,
      "edge": -0.20620639001101726,
      "adjustmentAmount": -14,
      "description": "All sports spreads (heavy favorite) underperforms market expectations by 21%",
      "warningText": "All sports spreads (heavy favorite) tracking at 50% (expected 71%) across 8 picks — pattern shows below-market performance",
      "lastUpdated": "2026-03-12T20:06:31.298Z",
      "dataSource": "combined",
      "statisticalConfidence": 0.3
    },
    {
      "id": "learned-NHL-team_total-C_tier",
      "type": "toxic",
      "sport": "NHL",
      "betType": "team_total",
      "oddsRange": "C_tier",
      "sampleSize": 16,
      "wins": 6,
      "losses": 10,
      "winRate": 0.375,
      "expectedWinRate": 0.5238095238095238,
      "edge": -0.14880952380952384,
      "adjustmentAmount": -12,
      "description": "NHL totals (C tier) underperforms market expectations by 15%",
      "warningText": "NHL totals (C tier) tracking at 38% (expected 52%) across 16 picks — pattern shows below-market performance",
      "lastUpdated": "2026-03-12T20:06:31.298Z",
      "dataSource": "combined",
      "statisticalConfidence": 0.55
    },
    {
      "id": "learned-NHL-moneyline-underdog",
      "type": "toxic",
      "sport": "NHL",
      "betType": "moneyline",
      "oddsRange": "underdog",
      "sampleSize": 16,
      "wins": 5,
      "losses": 11,
      "winRate": 0.3125,
      "expectedWinRate": 0.4509582863585118,
      "edge": -0.13845828635851182,
      "adjustmentAmount": -11,
      "description": "NHL ML (underdog) underperforms market expectations by 14%",
      "warningText": "NHL ML (underdog) tracking at 31% (expected 45%) across 16 picks — pattern shows below-market performance",
      "lastUpdated": "2026-03-12T20:06:31.298Z",
      "dataSource": "combined",
      "statisticalConfidence": 0.55
    },
    {
      "id": "learned-NHL-moneyline-C_tier",
      "type": "golden",
      "sport": "NHL",
      "betType": "moneyline",
      "oddsRange": "C_tier",
      "sampleSize": 60,
      "wins": 32,
      "losses": 28,
      "winRate": 0.5333333333333333,
      "expectedWinRate": 0.35767048495878384,
      "edge": 0.17566284837454949,
      "adjustmentAmount": 7,
      "description": "NHL ML (C tier) outperforms market expectations by 18%",
      "positiveCue": "NHL ML (C tier) tracking at 53% (expected 36%) across 60 picks — model generating edge here",
      "lastUpdated": "2026-03-12T20:06:31.298Z",
      "dataSource": "combined",
      "statisticalConfidence": 0.85
    },
    {
      "id": "learned-NBA-spread-C_tier",
      "type": "golden",
      "sport": "NBA",
      "betType": "spread",
      "oddsRange": "C_tier",
      "sampleSize": 50,
      "wins": 32,
      "losses": 18,
      "winRate": 0.64,
      "expectedWinRate": 0.5234464353793367,
      "edge": 0.11655356462066335,
      "adjustmentAmount": 6,
      "description": "NBA spreads (C tier) outperforms market expectations by 12%",
      "positiveCue": "NBA spreads (C tier) tracking at 64% (expected 52%) across 50 picks — model generating edge here",
      "lastUpdated": "2026-03-12T20:06:31.298Z",
      "dataSource": "combined",
      "statisticalConfidence": 0.85
    },
    {
      "id": "learned-NHL-moneyline-pick_em",
      "type": "golden",
      "sport": "NHL",
      "betType": "moneyline",
      "oddsRange": "pick_em",
      "sampleSize": 10,
      "wins": 7,
      "losses": 3,
      "winRate": 0.7,
      "expectedWinRate": 0.39135727328058423,
      "edge": 0.3086427267194157,
      "adjustmentAmount": 7,
      "description": "NHL ML (pick em) outperforms market expectations by 31%",
      "positiveCue": "NHL ML (pick em) tracking at 70% (expected 39%) across 10 picks — model generating edge here",
      "lastUpdated": "2026-03-12T20:06:31.298Z",
      "dataSource": "combined",
      "statisticalConfidence": 0.55
    },
    {
      "id": "learned-all-moneyline-pick_em",
      "type": "golden",
      "sport": "all",
      "betType": "moneyline",
      "oddsRange": "pick_em",
      "sampleSize": 27,
      "wins": 17,
      "losses": 10,
      "winRate": 0.6296296296296297,
      "expectedWinRate": 0.2628992628992629,
      "edge": 0.36673036673036674,
      "adjustmentAmount": 7,
      "description": "All sports ML (pick em) outperforms market expectations by 37%",
      "positiveCue": "All sports ML (pick em) tracking at 63% (expected 26%) across 27 picks — model generating edge here",
      "lastUpdated": "2026-03-12T20:06:31.298Z",
      "dataSource": "combined",
      "statisticalConfidence": 0.72
    },
    {
      "id": "learned-NCAAB-moneyline-heavy_favorite",
      "type": "toxic",
      "sport": "NCAAB",
      "betType": "moneyline",
      "oddsRange": "heavy_favorite",
      "sampleSize": 26,
      "wins": 12,
      "losses": 14,
      "winRate": 0.46153846153846156,
      "expectedWinRate": 0.900019227071717,
      "edge": -0.43848076553325543,
      "adjustmentAmount": -14,
      "description": "NCAAB ML (heavy favorite) underperforms market expectations by 44%",
      "warningText": "NCAAB ML (heavy favorite) tracking at 46% (expected 90%) across 26 picks — pattern shows below-market performance",
      "lastUpdated": "2026-03-12T20:06:31.298Z",
      "dataSource": "combined",
      "statisticalConfidence": 0.72
    },
    {
      "id": "learned-NCAAB-moneyline",
      "type": "toxic",
      "sport": "NCAAB",
      "betType": "moneyline",
      "sampleSize": 66,
      "wins": 35,
      "losses": 31,
      "winRate": 0.5303030303030303,
      "expectedWinRate": 0.8122172589410191,
      "edge": -0.2819142286379889,
      "adjustmentAmount": -14,
      "description": "NCAAB ML underperforms market expectations by 28%",
      "warningText": "NCAAB ML tracking at 53% (expected 81%) across 66 picks — pattern shows below-market performance",
      "lastUpdated": "2026-03-12T20:06:31.298Z",
      "dataSource": "combined",
      "statisticalConfidence": 0.85
    },
    {
      "id": "learned-NCAAB-moneyline-B_tier",
      "type": "toxic",
      "sport": "NCAAB",
      "betType": "moneyline",
      "oddsRange": "B_tier",
      "sampleSize": 36,
      "wins": 22,
      "losses": 14,
      "winRate": 0.6111111111111112,
      "expectedWinRate": 0.858551726847668,
      "edge": -0.24744061573655685,
      "adjustmentAmount": -14,
      "description": "NCAAB ML (B tier) underperforms market expectations by 25%",
      "warningText": "NCAAB ML (B tier) tracking at 61% (expected 86%) across 36 picks — pattern shows below-market performance",
      "lastUpdated": "2026-03-12T20:06:31.298Z",
      "dataSource": "combined",
      "statisticalConfidence": 0.72
    },
    {
      "id": "learned-NCAAB-total-B_tier",
      "type": "golden",
      "sport": "NCAAB",
      "betType": "total",
      "oddsRange": "B_tier",
      "sampleSize": 45,
      "wins": 29,
      "losses": 16,
      "winRate": 0.6444444444444445,
      "expectedWinRate": 0.5245139475908707,
      "edge": 0.11993049685357382,
      "adjustmentAmount": 6,
      "description": "NCAAB totals (B tier) outperforms market expectations by 12%",
      "positiveCue": "NCAAB totals (B tier) tracking at 64% (expected 52%) across 45 picks — model generating edge here",
      "lastUpdated": "2026-03-12T20:06:31.298Z",
      "dataSource": "combined",
      "statisticalConfidence": 0.85
    },
    {
      "id": "learned-NCAAB-team_total-favorite",
      "type": "golden",
      "sport": "NCAAB",
      "betType": "team_total",
      "oddsRange": "favorite",
      "sampleSize": 25,
      "wins": 18,
      "losses": 7,
      "winRate": 0.72,
      "expectedWinRate": 0.5238095238095238,
      "edge": 0.19619047619047614,
      "adjustmentAmount": 7,
      "description": "NCAAB totals (favorite) outperforms market expectations by 20%",
      "positiveCue": "NCAAB totals (favorite) tracking at 72% (expected 52%) across 25 picks — model generating edge here",
      "lastUpdated": "2026-03-12T20:06:31.298Z",
      "dataSource": "combined",
      "statisticalConfidence": 0.72
    },
    {
      "id": "learned-NCAAB-team_total",
      "type": "golden",
      "sport": "NCAAB",
      "betType": "team_total",
      "sampleSize": 25,
      "wins": 18,
      "losses": 7,
      "winRate": 0.72,
      "expectedWinRate": 0.5238095238095238,
      "edge": 0.19619047619047614,
      "adjustmentAmount": 7,
      "description": "NCAAB totals outperforms market expectations by 20%",
      "positiveCue": "NCAAB totals tracking at 72% (expected 52%) across 25 picks — model generating edge here",
      "lastUpdated": "2026-03-12T20:06:31.298Z",
      "dataSource": "combined",
      "statisticalConfidence": 0.72
    },
    {
      "id": "learned-NCAAB-team_total-C_tier",
      "type": "golden",
      "sport": "NCAAB",
      "betType": "team_total",
      "oddsRange": "C_tier",
      "sampleSize": 12,
      "wins": 10,
      "losses": 2,
      "winRate": 0.8333333333333334,
      "expectedWinRate": 0.5238095238095238,
      "edge": 0.30952380952380953,
      "adjustmentAmount": 7,
      "description": "NCAAB totals (C tier) outperforms market expectations by 31%",
      "positiveCue": "NCAAB totals (C tier) tracking at 83% (expected 52%) across 12 picks — model generating edge here",
      "lastUpdated": "2026-03-12T20:06:31.298Z",
      "dataSource": "combined",
      "statisticalConfidence": 0.55
    },
    {
      "id": "learned-NCAAB-moneyline-C_tier",
      "type": "toxic",
      "sport": "NCAAB",
      "betType": "moneyline",
      "oddsRange": "C_tier",
      "sampleSize": 20,
      "wins": 7,
      "losses": 13,
      "winRate": 0.35,
      "expectedWinRate": 0.7094290280400989,
      "edge": -0.3594290280400989,
      "adjustmentAmount": -14,
      "description": "NCAAB ML (C tier) underperforms market expectations by 36%",
      "warningText": "NCAAB ML (C tier) tracking at 35% (expected 71%) across 20 picks — pattern shows below-market performance",
      "lastUpdated": "2026-03-12T20:06:31.298Z",
      "dataSource": "combined",
      "statisticalConfidence": 0.72
    },
    {
      "id": "learned-NBA-moneyline-pick_em",
      "type": "golden",
      "sport": "NBA",
      "betType": "moneyline",
      "oddsRange": "pick_em",
      "sampleSize": 14,
      "wins": 8,
      "losses": 6,
      "winRate": 0.5714285714285714,
      "expectedWinRate": 0.13580246913580246,
      "edge": 0.43562610229276894,
      "adjustmentAmount": 7,
      "description": "NBA ML (pick em) outperforms market expectations by 44%",
      "positiveCue": "NBA ML (pick em) tracking at 57% (expected 14%) across 14 picks — model generating edge here",
      "lastUpdated": "2026-03-12T20:06:31.298Z",
      "dataSource": "combined",
      "statisticalConfidence": 0.55
    },
    {
      "id": "prior-ncaab-heavy-fav-spread",
      "type": "toxic",
      "sport": "NCAAB",
      "betType": "spread",
      "oddsRange": "heavy_favorite",
      "sampleSize": 15,
      "wins": 7,
      "losses": 8,
      "winRate": 0.467,
      "expectedWinRate": 0.524,
      "edge": -0.057,
      "adjustmentAmount": -5,
      "description": "NCAAB heavy favorites vs. spread underperform expectations",
      "warningText": "NCAAB blowout lines historically push or miss — sharps fade heavy chalk in college basketball",
      "lastUpdated": "2026-03-12T20:06:31.298Z",
      "dataSource": "prior",
      "statisticalConfidence": 0.3
    },
    {
      "id": "prior-nba-total-road-game",
      "type": "golden",
      "sport": "NBA",
      "betType": "total",
      "sampleSize": 22,
      "wins": 14,
      "losses": 8,
      "winRate": 0.636,
      "expectedWinRate": 0.524,
      "edge": 0.112,
      "adjustmentAmount": 4,
      "description": "NBA totals show consistent edge when model identifies mis-priced lines",
      "positiveCue": "NBA total market has historically rewarded analytical edge — model tracks well here",
      "lastUpdated": "2026-03-12T20:06:31.298Z",
      "dataSource": "prior",
      "statisticalConfidence": 0.35
    },
    {
      "id": "prior-nfl-road-underdog-spread",
      "type": "golden",
      "sport": "NFL",
      "betType": "spread",
      "oddsRange": "underdog",
      "sampleSize": 18,
      "wins": 11,
      "losses": 7,
      "winRate": 0.611,
      "expectedWinRate": 0.524,
      "edge": 0.087,
      "adjustmentAmount": 3,
      "description": "NFL road underdogs cover more than favorites expect — public money overweights home teams",
      "positiveCue": "Road underdog value historically strong in the NFL — public bias creates edge",
      "lastUpdated": "2026-03-12T20:06:31.298Z",
      "dataSource": "prior",
      "statisticalConfidence": 0.3
    },
    {
      "id": "prior-nhl-total-under",
      "type": "neutral",
      "sport": "NHL",
      "betType": "total",
      "sampleSize": 12,
      "wins": 6,
      "losses": 6,
      "winRate": 0.5,
      "expectedWinRate": 0.524,
      "edge": -0.024,
      "adjustmentAmount": 0,
      "description": "NHL totals near market equilibrium — neither systematic edge nor drag detected",
      "lastUpdated": "2026-03-12T20:06:31.298Z",
      "dataSource": "prior",
      "statisticalConfidence": 0.25
    }
  ],
  "engineVersion": "1.0.0"
}