{
  "totalPatterns": 32,
  "toxicPatterns": 14,
  "goldenPatterns": 17,
  "totalSettledPicks": 886,
  "lastRunAt": "2026-03-09T21:42:21.020Z",
  "nextRunAt": "2026-03-09T22:02:21.020Z",
  "patterns": [
    {
      "id": "learned-NBA-moneyline-heavy_underdog",
      "type": "golden",
      "sport": "NBA",
      "betType": "moneyline",
      "oddsRange": "heavy_underdog",
      "sampleSize": 10,
      "wins": 8,
      "losses": 2,
      "winRate": 0.8,
      "expectedWinRate": 0.19786307874950534,
      "edge": 0.6021369212504947,
      "adjustmentAmount": 7,
      "description": "NBA ML (heavy underdog) outperforms market expectations by 60%",
      "positiveCue": "NBA ML (heavy underdog) tracking at 80% (expected 20%) across 10 picks — model generating edge here",
      "lastUpdated": "2026-03-09T21:42:21.019Z",
      "dataSource": "combined",
      "statisticalConfidence": 0.55
    },
    {
      "id": "learned-NBA-moneyline",
      "type": "golden",
      "sport": "NBA",
      "betType": "moneyline",
      "sampleSize": 236,
      "wins": 135,
      "losses": 101,
      "winRate": 0.5720338983050848,
      "expectedWinRate": 0.4497295280731207,
      "edge": 0.12230437023196405,
      "adjustmentAmount": 6,
      "description": "NBA ML outperforms market expectations by 12%",
      "positiveCue": "NBA ML tracking at 57% (expected 45%) across 236 picks — model generating edge here",
      "lastUpdated": "2026-03-09T21:42:21.019Z",
      "dataSource": "combined",
      "statisticalConfidence": 0.95
    },
    {
      "id": "learned-all-moneyline-heavy_underdog",
      "type": "golden",
      "sport": "all",
      "betType": "moneyline",
      "oddsRange": "heavy_underdog",
      "sampleSize": 11,
      "wins": 8,
      "losses": 3,
      "winRate": 0.7272727272727273,
      "expectedWinRate": 0.20404377666481174,
      "edge": 0.5232289506079155,
      "adjustmentAmount": 7,
      "description": "All sports ML (heavy underdog) outperforms market expectations by 52%",
      "positiveCue": "All sports ML (heavy underdog) tracking at 73% (expected 20%) across 11 picks — model generating edge here",
      "lastUpdated": "2026-03-09T21:42:21.019Z",
      "dataSource": "combined",
      "statisticalConfidence": 0.55
    },
    {
      "id": "learned-NBA-moneyline-B_tier",
      "type": "golden",
      "sport": "NBA",
      "betType": "moneyline",
      "oddsRange": "B_tier",
      "sampleSize": 25,
      "wins": 13,
      "losses": 12,
      "winRate": 0.52,
      "expectedWinRate": 0.05087319665907365,
      "edge": 0.4691268033409264,
      "adjustmentAmount": 7,
      "description": "NBA ML (B tier) outperforms market expectations by 47%",
      "positiveCue": "NBA ML (B tier) tracking at 52% (expected 5%) across 25 picks — model generating edge here",
      "lastUpdated": "2026-03-09T21:42:21.019Z",
      "dataSource": "combined",
      "statisticalConfidence": 0.72
    },
    {
      "id": "learned-NBA-spread-pick_em",
      "type": "toxic",
      "sport": "NBA",
      "betType": "spread",
      "oddsRange": "pick_em",
      "sampleSize": 8,
      "wins": 3,
      "losses": 5,
      "winRate": 0.375,
      "expectedWinRate": 0.517490952955368,
      "edge": -0.14249095295536796,
      "adjustmentAmount": -11,
      "description": "NBA spreads (pick em) underperforms market expectations by 14%",
      "warningText": "NBA spreads (pick em) tracking at 38% (expected 52%) across 8 picks — pattern shows below-market performance",
      "lastUpdated": "2026-03-09T21:42:21.019Z",
      "dataSource": "combined",
      "statisticalConfidence": 0.3
    },
    {
      "id": "learned-all-total-pick_em",
      "type": "toxic",
      "sport": "all",
      "betType": "total",
      "oddsRange": "pick_em",
      "sampleSize": 11,
      "wins": 3,
      "losses": 8,
      "winRate": 0.2727272727272727,
      "expectedWinRate": 0.40636805180787916,
      "edge": -0.13364077908060645,
      "adjustmentAmount": -11,
      "description": "All sports totals (pick em) underperforms market expectations by 13%",
      "warningText": "All sports totals (pick em) tracking at 27% (expected 41%) across 11 picks — pattern shows below-market performance",
      "lastUpdated": "2026-03-09T21:42:21.019Z",
      "dataSource": "combined",
      "statisticalConfidence": 0.55
    },
    {
      "id": "learned-all-moneyline-heavy_favorite",
      "type": "toxic",
      "sport": "all",
      "betType": "moneyline",
      "oddsRange": "heavy_favorite",
      "sampleSize": 28,
      "wins": 13,
      "losses": 15,
      "winRate": 0.4642857142857143,
      "expectedWinRate": 0.8952566212778692,
      "edge": -0.4309709069921549,
      "adjustmentAmount": -14,
      "description": "All sports ML (heavy favorite) underperforms market expectations by 43%",
      "warningText": "All sports ML (heavy favorite) tracking at 46% (expected 90%) across 28 picks — pattern shows below-market performance",
      "lastUpdated": "2026-03-09T21:42:21.019Z",
      "dataSource": "combined",
      "statisticalConfidence": 0.72
    },
    {
      "id": "learned-NBA-moneyline-C_tier",
      "type": "golden",
      "sport": "NBA",
      "betType": "moneyline",
      "oddsRange": "C_tier",
      "sampleSize": 37,
      "wins": 19,
      "losses": 18,
      "winRate": 0.5135135135135135,
      "expectedWinRate": 0.0037695207323640285,
      "edge": 0.5097439927811495,
      "adjustmentAmount": 7,
      "description": "NBA ML (C tier) outperforms market expectations by 51%",
      "positiveCue": "NBA ML (C tier) tracking at 51% (expected 0%) across 37 picks — model generating edge here",
      "lastUpdated": "2026-03-09T21:42:21.019Z",
      "dataSource": "combined",
      "statisticalConfidence": 0.72
    },
    {
      "id": "learned-NHL-moneyline-favorite",
      "type": "golden",
      "sport": "NHL",
      "betType": "moneyline",
      "oddsRange": "favorite",
      "sampleSize": 165,
      "wins": 112,
      "losses": 53,
      "winRate": 0.6787878787878788,
      "expectedWinRate": 0.5333710407239819,
      "edge": 0.14541683806389694,
      "adjustmentAmount": 7,
      "description": "NHL ML (favorite) outperforms market expectations by 15%",
      "positiveCue": "NHL ML (favorite) tracking at 68% (expected 53%) across 165 picks — model generating edge here",
      "lastUpdated": "2026-03-09T21:42:21.019Z",
      "dataSource": "combined",
      "statisticalConfidence": 0.95
    },
    {
      "id": "learned-NHL-moneyline",
      "type": "golden",
      "sport": "NHL",
      "betType": "moneyline",
      "sampleSize": 190,
      "wins": 122,
      "losses": 68,
      "winRate": 0.6421052631578947,
      "expectedWinRate": 0.47378624643420947,
      "edge": 0.16831901672368527,
      "adjustmentAmount": 7,
      "description": "NHL ML outperforms market expectations by 17%",
      "positiveCue": "NHL ML tracking at 64% (expected 47%) across 190 picks — model generating edge here",
      "lastUpdated": "2026-03-09T21:42:21.019Z",
      "dataSource": "combined",
      "statisticalConfidence": 0.95
    },
    {
      "id": "learned-NHL-moneyline-B_tier",
      "type": "golden",
      "sport": "NHL",
      "betType": "moneyline",
      "oddsRange": "B_tier",
      "sampleSize": 18,
      "wins": 12,
      "losses": 6,
      "winRate": 0.6666666666666666,
      "expectedWinRate": 0.48424068767908307,
      "edge": 0.18242597898758356,
      "adjustmentAmount": 7,
      "description": "NHL ML (B tier) outperforms market expectations by 18%",
      "positiveCue": "NHL ML (B tier) tracking at 67% (expected 48%) across 18 picks — model generating edge here",
      "lastUpdated": "2026-03-09T21:42:21.019Z",
      "dataSource": "combined",
      "statisticalConfidence": 0.55
    },
    {
      "id": "learned-NHL-spread-underdog",
      "type": "toxic",
      "sport": "NHL",
      "betType": "spread",
      "oddsRange": "underdog",
      "sampleSize": 8,
      "wins": 2,
      "losses": 6,
      "winRate": 0.25,
      "expectedWinRate": 0.372960372960373,
      "edge": -0.12296037296037299,
      "adjustmentAmount": -10,
      "description": "NHL spreads (underdog) underperforms market expectations by 12%",
      "warningText": "NHL spreads (underdog) tracking at 25% (expected 37%) across 8 picks — pattern shows below-market performance",
      "lastUpdated": "2026-03-09T21:42:21.019Z",
      "dataSource": "combined",
      "statisticalConfidence": 0.3
    },
    {
      "id": "learned-all-spread-underdog",
      "type": "toxic",
      "sport": "all",
      "betType": "spread",
      "oddsRange": "underdog",
      "sampleSize": 8,
      "wins": 2,
      "losses": 6,
      "winRate": 0.25,
      "expectedWinRate": 0.372960372960373,
      "edge": -0.12296037296037299,
      "adjustmentAmount": -10,
      "description": "All sports spreads (underdog) underperforms market expectations by 12%",
      "warningText": "All sports spreads (underdog) tracking at 25% (expected 37%) across 8 picks — pattern shows below-market performance",
      "lastUpdated": "2026-03-09T21:42:21.019Z",
      "dataSource": "combined",
      "statisticalConfidence": 0.3
    },
    {
      "id": "learned-NHL-spread-B_tier",
      "type": "golden",
      "sport": "NHL",
      "betType": "spread",
      "oddsRange": "B_tier",
      "sampleSize": 18,
      "wins": 13,
      "losses": 5,
      "winRate": 0.7222222222222222,
      "expectedWinRate": 0.31166347992351817,
      "edge": 0.41055874229870404,
      "adjustmentAmount": 7,
      "description": "NHL spreads (B tier) outperforms market expectations by 41%",
      "positiveCue": "NHL spreads (B tier) tracking at 72% (expected 31%) across 18 picks — model generating edge here",
      "lastUpdated": "2026-03-09T21:42:21.019Z",
      "dataSource": "combined",
      "statisticalConfidence": 0.55
    },
    {
      "id": "learned-NHL-spread-heavy_favorite",
      "type": "toxic",
      "sport": "NHL",
      "betType": "spread",
      "oddsRange": "heavy_favorite",
      "sampleSize": 8,
      "wins": 4,
      "losses": 4,
      "winRate": 0.5,
      "expectedWinRate": 0.7062063900110173,
      "edge": -0.20620639001101726,
      "adjustmentAmount": -14,
      "description": "NHL spreads (heavy favorite) underperforms market expectations by 21%",
      "warningText": "NHL spreads (heavy favorite) tracking at 50% (expected 71%) across 8 picks — pattern shows below-market performance",
      "lastUpdated": "2026-03-09T21:42:21.019Z",
      "dataSource": "combined",
      "statisticalConfidence": 0.3
    },
    {
      "id": "learned-all-spread-heavy_favorite",
      "type": "toxic",
      "sport": "all",
      "betType": "spread",
      "oddsRange": "heavy_favorite",
      "sampleSize": 8,
      "wins": 4,
      "losses": 4,
      "winRate": 0.5,
      "expectedWinRate": 0.7062063900110173,
      "edge": -0.20620639001101726,
      "adjustmentAmount": -14,
      "description": "All sports spreads (heavy favorite) underperforms market expectations by 21%",
      "warningText": "All sports spreads (heavy favorite) tracking at 50% (expected 71%) across 8 picks — pattern shows below-market performance",
      "lastUpdated": "2026-03-09T21:42:21.019Z",
      "dataSource": "combined",
      "statisticalConfidence": 0.3
    },
    {
      "id": "learned-NHL-team_total-C_tier",
      "type": "toxic",
      "sport": "NHL",
      "betType": "team_total",
      "oddsRange": "C_tier",
      "sampleSize": 16,
      "wins": 6,
      "losses": 10,
      "winRate": 0.375,
      "expectedWinRate": 0.5238095238095238,
      "edge": -0.14880952380952384,
      "adjustmentAmount": -12,
      "description": "NHL totals (C tier) underperforms market expectations by 15%",
      "warningText": "NHL totals (C tier) tracking at 38% (expected 52%) across 16 picks — pattern shows below-market performance",
      "lastUpdated": "2026-03-09T21:42:21.019Z",
      "dataSource": "combined",
      "statisticalConfidence": 0.55
    },
    {
      "id": "learned-NHL-moneyline-underdog",
      "type": "toxic",
      "sport": "NHL",
      "betType": "moneyline",
      "oddsRange": "underdog",
      "sampleSize": 16,
      "wins": 5,
      "losses": 11,
      "winRate": 0.3125,
      "expectedWinRate": 0.4509582863585118,
      "edge": -0.13845828635851182,
      "adjustmentAmount": -11,
      "description": "NHL ML (underdog) underperforms market expectations by 14%",
      "warningText": "NHL ML (underdog) tracking at 31% (expected 45%) across 16 picks — pattern shows below-market performance",
      "lastUpdated": "2026-03-09T21:42:21.019Z",
      "dataSource": "combined",
      "statisticalConfidence": 0.55
    },
    {
      "id": "learned-NHL-moneyline-C_tier",
      "type": "golden",
      "sport": "NHL",
      "betType": "moneyline",
      "oddsRange": "C_tier",
      "sampleSize": 46,
      "wins": 22,
      "losses": 24,
      "winRate": 0.4782608695652174,
      "expectedWinRate": 0.2528828975150235,
      "edge": 0.2253779720501939,
      "adjustmentAmount": 7,
      "description": "NHL ML (C tier) outperforms market expectations by 23%",
      "positiveCue": "NHL ML (C tier) tracking at 48% (expected 25%) across 46 picks — model generating edge here",
      "lastUpdated": "2026-03-09T21:42:21.019Z",
      "dataSource": "combined",
      "statisticalConfidence": 0.85
    },
    {
      "id": "learned-all-moneyline-pick_em",
      "type": "golden",
      "sport": "all",
      "betType": "moneyline",
      "oddsRange": "pick_em",
      "sampleSize": 21,
      "wins": 12,
      "losses": 9,
      "winRate": 0.5714285714285714,
      "expectedWinRate": 0.3560257589696412,
      "edge": 0.21540281245893017,
      "adjustmentAmount": 7,
      "description": "All sports ML (pick em) outperforms market expectations by 22%",
      "positiveCue": "All sports ML (pick em) tracking at 57% (expected 36%) across 21 picks — model generating edge here",
      "lastUpdated": "2026-03-09T21:42:21.019Z",
      "dataSource": "combined",
      "statisticalConfidence": 0.72
    },
    {
      "id": "learned-NCAAB-moneyline-heavy_favorite",
      "type": "toxic",
      "sport": "NCAAB",
      "betType": "moneyline",
      "oddsRange": "heavy_favorite",
      "sampleSize": 21,
      "wins": 9,
      "losses": 12,
      "winRate": 0.42857142857142855,
      "expectedWinRate": 0.9142016669390424,
      "edge": -0.4856302383676138,
      "adjustmentAmount": -14,
      "description": "NCAAB ML (heavy favorite) underperforms market expectations by 49%",
      "warningText": "NCAAB ML (heavy favorite) tracking at 43% (expected 91%) across 21 picks — pattern shows below-market performance",
      "lastUpdated": "2026-03-09T21:42:21.019Z",
      "dataSource": "combined",
      "statisticalConfidence": 0.72
    },
    {
      "id": "learned-NCAAB-moneyline",
      "type": "toxic",
      "sport": "NCAAB",
      "betType": "moneyline",
      "sampleSize": 45,
      "wins": 25,
      "losses": 20,
      "winRate": 0.5555555555555556,
      "expectedWinRate": 0.8477775522630404,
      "edge": -0.29222199670748483,
      "adjustmentAmount": -14,
      "description": "NCAAB ML underperforms market expectations by 29%",
      "warningText": "NCAAB ML tracking at 56% (expected 85%) across 45 picks — pattern shows below-market performance",
      "lastUpdated": "2026-03-09T21:42:21.019Z",
      "dataSource": "combined",
      "statisticalConfidence": 0.85
    },
    {
      "id": "learned-NCAAB-moneyline-B_tier",
      "type": "toxic",
      "sport": "NCAAB",
      "betType": "moneyline",
      "oddsRange": "B_tier",
      "sampleSize": 22,
      "wins": 16,
      "losses": 6,
      "winRate": 0.7272727272727273,
      "expectedWinRate": 0.8991935483870968,
      "edge": -0.17192082111436946,
      "adjustmentAmount": -14,
      "description": "NCAAB ML (B tier) underperforms market expectations by 17%",
      "warningText": "NCAAB ML (B tier) tracking at 73% (expected 90%) across 22 picks — pattern shows below-market performance",
      "lastUpdated": "2026-03-09T21:42:21.019Z",
      "dataSource": "combined",
      "statisticalConfidence": 0.72
    },
    {
      "id": "learned-NCAAB-team_total-favorite",
      "type": "golden",
      "sport": "NCAAB",
      "betType": "team_total",
      "oddsRange": "favorite",
      "sampleSize": 25,
      "wins": 18,
      "losses": 7,
      "winRate": 0.72,
      "expectedWinRate": 0.5238095238095238,
      "edge": 0.19619047619047614,
      "adjustmentAmount": 7,
      "description": "NCAAB totals (favorite) outperforms market expectations by 20%",
      "positiveCue": "NCAAB totals (favorite) tracking at 72% (expected 52%) across 25 picks — model generating edge here",
      "lastUpdated": "2026-03-09T21:42:21.019Z",
      "dataSource": "combined",
      "statisticalConfidence": 0.72
    },
    {
      "id": "learned-NCAAB-team_total",
      "type": "golden",
      "sport": "NCAAB",
      "betType": "team_total",
      "sampleSize": 25,
      "wins": 18,
      "losses": 7,
      "winRate": 0.72,
      "expectedWinRate": 0.5238095238095238,
      "edge": 0.19619047619047614,
      "adjustmentAmount": 7,
      "description": "NCAAB totals outperforms market expectations by 20%",
      "positiveCue": "NCAAB totals tracking at 72% (expected 52%) across 25 picks — model generating edge here",
      "lastUpdated": "2026-03-09T21:42:21.019Z",
      "dataSource": "combined",
      "statisticalConfidence": 0.72
    },
    {
      "id": "learned-NCAAB-team_total-C_tier",
      "type": "golden",
      "sport": "NCAAB",
      "betType": "team_total",
      "oddsRange": "C_tier",
      "sampleSize": 12,
      "wins": 10,
      "losses": 2,
      "winRate": 0.8333333333333334,
      "expectedWinRate": 0.5238095238095238,
      "edge": 0.30952380952380953,
      "adjustmentAmount": 7,
      "description": "NCAAB totals (C tier) outperforms market expectations by 31%",
      "positiveCue": "NCAAB totals (C tier) tracking at 83% (expected 52%) across 12 picks — model generating edge here",
      "lastUpdated": "2026-03-09T21:42:21.019Z",
      "dataSource": "combined",
      "statisticalConfidence": 0.55
    },
    {
      "id": "learned-NCAAB-moneyline-C_tier",
      "type": "toxic",
      "sport": "NCAAB",
      "betType": "moneyline",
      "oddsRange": "C_tier",
      "sampleSize": 20,
      "wins": 7,
      "losses": 13,
      "winRate": 0.35,
      "expectedWinRate": 0.7094290280400989,
      "edge": -0.3594290280400989,
      "adjustmentAmount": -14,
      "description": "NCAAB ML (C tier) underperforms market expectations by 36%",
      "warningText": "NCAAB ML (C tier) tracking at 35% (expected 71%) across 20 picks — pattern shows below-market performance",
      "lastUpdated": "2026-03-09T21:42:21.019Z",
      "dataSource": "combined",
      "statisticalConfidence": 0.72
    },
    {
      "id": "learned-NBA-moneyline-pick_em",
      "type": "golden",
      "sport": "NBA",
      "betType": "moneyline",
      "oddsRange": "pick_em",
      "sampleSize": 10,
      "wins": 5,
      "losses": 5,
      "winRate": 0.5,
      "expectedWinRate": 0.3861264579496623,
      "edge": 0.11387354205033767,
      "adjustmentAmount": 6,
      "description": "NBA ML (pick em) outperforms market expectations by 11%",
      "positiveCue": "NBA ML (pick em) tracking at 50% (expected 39%) across 10 picks — model generating edge here",
      "lastUpdated": "2026-03-09T21:42:21.019Z",
      "dataSource": "combined",
      "statisticalConfidence": 0.55
    },
    {
      "id": "prior-ncaab-heavy-fav-spread",
      "type": "toxic",
      "sport": "NCAAB",
      "betType": "spread",
      "oddsRange": "heavy_favorite",
      "sampleSize": 15,
      "wins": 7,
      "losses": 8,
      "winRate": 0.467,
      "expectedWinRate": 0.524,
      "edge": -0.057,
      "adjustmentAmount": -5,
      "description": "NCAAB heavy favorites vs. spread underperform expectations",
      "warningText": "NCAAB blowout lines historically push or miss — sharps fade heavy chalk in college basketball",
      "lastUpdated": "2026-03-09T21:42:21.020Z",
      "dataSource": "prior",
      "statisticalConfidence": 0.3
    },
    {
      "id": "prior-nba-total-road-game",
      "type": "golden",
      "sport": "NBA",
      "betType": "total",
      "sampleSize": 22,
      "wins": 14,
      "losses": 8,
      "winRate": 0.636,
      "expectedWinRate": 0.524,
      "edge": 0.112,
      "adjustmentAmount": 4,
      "description": "NBA totals show consistent edge when model identifies mis-priced lines",
      "positiveCue": "NBA total market has historically rewarded analytical edge — model tracks well here",
      "lastUpdated": "2026-03-09T21:42:21.020Z",
      "dataSource": "prior",
      "statisticalConfidence": 0.35
    },
    {
      "id": "prior-nfl-road-underdog-spread",
      "type": "golden",
      "sport": "NFL",
      "betType": "spread",
      "oddsRange": "underdog",
      "sampleSize": 18,
      "wins": 11,
      "losses": 7,
      "winRate": 0.611,
      "expectedWinRate": 0.524,
      "edge": 0.087,
      "adjustmentAmount": 3,
      "description": "NFL road underdogs cover more than favorites expect — public money overweights home teams",
      "positiveCue": "Road underdog value historically strong in the NFL — public bias creates edge",
      "lastUpdated": "2026-03-09T21:42:21.020Z",
      "dataSource": "prior",
      "statisticalConfidence": 0.3
    },
    {
      "id": "prior-nhl-total-under",
      "type": "neutral",
      "sport": "NHL",
      "betType": "total",
      "sampleSize": 12,
      "wins": 6,
      "losses": 6,
      "winRate": 0.5,
      "expectedWinRate": 0.524,
      "edge": -0.024,
      "adjustmentAmount": 0,
      "description": "NHL totals near market equilibrium — neither systematic edge nor drag detected",
      "lastUpdated": "2026-03-09T21:42:21.020Z",
      "dataSource": "prior",
      "statisticalConfidence": 0.25
    }
  ],
  "engineVersion": "1.0.0"
}